bes_dev_kit/__init__.py
bes_dev_kit/__main__.py
bes_dev_kit/cli.py
bes_dev_kit/config.py
bes_dev_kit/src/create_ossp_master.py
bes_dev_kit/src/create_version_data.py
bes_dev_kit/src/generate_report.py
bes_dev_kit/src/risk_assessment.py
bes_dev_kit/src/risk_summary/License_compliance.py
bes_dev_kit/src/risk_summary/New_line_char.py
bes_dev_kit/src/risk_summary/Objective.py
bes_dev_kit/src/risk_summary/Sbom_report.py
bes_dev_kit/src/risk_summary/Scorecard_report.py
bes_dev_kit/src/risk_summary/Static_code_analysis.py
bes_dev_kit/src/validate_report_file.py
bes_dev_kit/src/validate_version_file.py
besecure_developer_toolkit-0.0.8.dist-info/LICENSE
besecure_developer_toolkit-0.0.8.dist-info/METADATA
besecure_developer_toolkit-0.0.8.dist-info/WHEEL
besecure_developer_toolkit-0.0.8.dist-info/entry_points.txt
besecure_developer_toolkit-0.0.8.dist-info/RECORD
