Metadata-Version: 2.1
Name: besecure-developer-toolkit
Version: 0.0.8
Summary: cli tool for generating metadata and assessment report for [BeSLighthouse](https://github.com/Be-Secure/BeSLighthouse).
Author: asa1997
Author-email: arunsureshampadath@gmail.com
Requires-Python: >=3.10,<4.0
Classifier: Programming Language :: Python :: 3
Classifier: Programming Language :: Python :: 3.10
Classifier: Programming Language :: Python :: 3.11
Classifier: Programming Language :: Python :: 3.12
Requires-Dist: pytest (>=7.3.0,<8.0.0)
Requires-Dist: reportlab (>=3.6.8,<4.0.0)
Requires-Dist: requests (>=2.29.0,<3.0.0)
Requires-Dist: typer[all] (>=0.9.0,<0.10.0)
